hv4gha/__init__.py
hv4gha/entry.py
hv4gha/gh.py
hv4gha/helpers.py
hv4gha/py.typed
hv4gha/vault.py
hv4gha-0.4.1.dist-info/METADATA
hv4gha-0.4.1.dist-info/WHEEL
hv4gha-0.4.1.dist-info/licenses/LICENSE
hv4gha-0.4.1.dist-info/RECORD
