Metadata-Version: 2.4
Name: hv4gha
Version: 0.4.1
Summary: Use HashiCorp Vault to manage a GitHub App's private RSA key.
License-File: LICENSE
Author: Andreas Olsson
Author-email: andreas@arrakis.se
Requires-Python: >=3.10, <3.15
Classifier: License :: OSI Approved :: MIT License
Classifier: Programming Language :: Python :: 3
Classifier: Programming Language :: Python :: 3.10
Classifier: Programming Language :: Python :: 3.11
Classifier: Programming Language :: Python :: 3.12
Classifier: Programming Language :: Python :: 3.13
Classifier: Programming Language :: Python :: 3.14
Requires-Dist: certifi (>=2025.10.5)
Requires-Dist: cffi (>=2.0.0)
Requires-Dist: cryptography (>=43.0.1)
Requires-Dist: pydantic (>=2.12.0,<3)
Requires-Dist: requests (>=2.31.0,<3)
Project-URL: Repository, https://github.com/andreaso/hv4gha
